<?xml version="1.0" encoding="utf-8" ?>
<Defs>
	<KCSG.SymbolDef>
		<defName>Wall_AM_BlocksPristineLimestone_Kemetic</defName>
		<thing>Wall</thing>
		<stuff>AM_BlocksPristineLimestone</stuff>
		<styleCategory>AM_Kemetic</styleCategory>
	</KCSG.SymbolDef>
	<KCSG.SymbolDef>
		<defName>AM_GrandGate_AM_BlocksPristineLimestone</defName>
		<thing>AM_GrandGate</thing>
		<stuff>AM_BlocksPristineLimestone</stuff>
	</KCSG.SymbolDef>
	<KCSG.SymbolDef>
		<defName>Column_AM_BlocksPristineLimestone_Kemetic</defName>
		<thing>Column</thing>
		<stuff>AM_BlocksPristineLimestone</stuff>
		<styleCategory>AM_Kemetic</styleCategory>
	</KCSG.SymbolDef>
	<KCSG.SymbolDef>
		<defName>Door_AM_BlocksPristineLimestone_Kemetic</defName>
		<thing>Door</thing>
		<stuff>AM_BlocksPristineLimestone</stuff>
		<styleCategory>AM_Kemetic</styleCategory>
	</KCSG.SymbolDef>
	<KCSG.SymbolDef>
		<defName>Table3x3c_AM_BlocksPristineLimestone_Kemetic</defName>
		<thing>Table3x3c</thing>
		<stuff>AM_BlocksPristineLimestone</stuff>
		<styleCategory>AM_Kemetic</styleCategory>
	</KCSG.SymbolDef>
	<KCSG.SymbolDef>
		<defName>TorchWallLamp_Kemetic_East</defName>
		<thing>TorchWallLamp</thing>
		<styleCategory>AM_Kemetic</styleCategory>
		<rotation>East</rotation>
	</KCSG.SymbolDef>
	<KCSG.SymbolDef>
		<defName>TorchWallLamp_Kemetic_West</defName>
		<thing>TorchWallLamp</thing>
		<styleCategory>AM_Kemetic</styleCategory>
		<rotation>West</rotation>
	</KCSG.SymbolDef>
	<KCSG.SymbolDef>
		<defName>Pew_AM_BlocksPristineLimestone_Kemetic_North</defName>
		<thing>Pew</thing>
		<stuff>AM_BlocksPristineLimestone</stuff>
		<styleCategory>AM_Kemetic</styleCategory>
	</KCSG.SymbolDef>
	<KCSG.SymbolDef>
		<defName>Shelf_AM_BlocksPristineLimestone_Kemetic_West</defName>
		<thing>Shelf</thing>
		<stuff>AM_BlocksPristineLimestone</stuff>
		<styleCategory>AM_Kemetic</styleCategory>
		<rotation>West</rotation>
	</KCSG.SymbolDef>
	<KCSG.SymbolDef>
		<defName>Shelf_AM_BlocksPristineLimestone_Kemetic_East</defName>
		<thing>Shelf</thing>
		<stuff>AM_BlocksPristineLimestone</stuff>
		<styleCategory>AM_Kemetic</styleCategory>
		<rotation>East</rotation>
	</KCSG.SymbolDef>
	<KCSG.SymbolDef>
		<defName>Dresser_AM_BlocksPristineLimestone_Kemetic_West</defName>
		<thing>Dresser</thing>
		<stuff>AM_BlocksPristineLimestone</stuff>
		<styleCategory>AM_Kemetic</styleCategory>
		<rotation>West</rotation>
	</KCSG.SymbolDef>
	<KCSG.SymbolDef>
		<defName>Dresser_AM_BlocksPristineLimestone_Kemetic_East</defName>
		<thing>Dresser</thing>
		<stuff>AM_BlocksPristineLimestone</stuff>
		<styleCategory>AM_Kemetic</styleCategory>
		<rotation>East</rotation>
	</KCSG.SymbolDef>
	<KCSG.SymbolDef>
		<defName>Ideogram_Kemetic_North</defName>
		<thing>Ideogram</thing>
		<styleCategory>AM_Kemetic</styleCategory>
	</KCSG.SymbolDef>
	<KCSG.SymbolDef>
		<defName>EndTable_AM_BlocksPristineLimestone_Kemetic_South</defName>
		<thing>EndTable</thing>
		<stuff>AM_BlocksPristineLimestone</stuff>
		<styleCategory>AM_Kemetic</styleCategory>
		<rotation>South</rotation>
	</KCSG.SymbolDef>
	<KCSG.SymbolDef>
		<defName>TorchLamp_Kemetic</defName>
		<thing>TorchLamp</thing>
		<styleCategory>AM_Kemetic</styleCategory>
	</KCSG.SymbolDef>
	<KCSG.SymbolDef>
		<defName>Altar_Medium_AM_BlocksPristineLimestone_Kemetic_North</defName>
		<thing>Altar_Medium</thing>
		<stuff>AM_BlocksPristineLimestone</stuff>
		<styleCategory>AM_Kemetic</styleCategory>
	</KCSG.SymbolDef>
</Defs>